[{"type":"ProductionLeader","production":{"input":[1,0,0,0,0,0,0],"restoreinput":[1,0,0,0,0,0,0],"output":[0,0,0,0,1,0,1],"restoreoutput":[0,0,0,0,1,0,1]},"state":"INACTIVE","victoryPoints":4,"requirementsResources":[],"requirementsCards":[{"key":"GREEN","value":1}],"requirementsCardsLevel":2},{"type":"ProductionLeader","production":{"input":[0,0,0,1,0,0,0],"restoreinput":[0,0,0,1,0,0,0],"output":[0,0,0,0,1,0,1],"restoreoutput":[0,0,0,0,1,0,1]},"state":"INACTIVE","victoryPoints":4,"requirementsResources":[],"requirementsCards":[{"key":"PURPLE","value":1}],"requirementsCardsLevel":2},{"type":"ProductionLeader","production":{"input":[0,1,0,0,0,0,0],"restoreinput":[0,1,0,0,0,0,0],"output":[0,0,0,0,1,0,1],"restoreoutput":[0,0,0,0,1,0,1]},"state":"INACTIVE","victoryPoints":4,"requirementsResources":[],"requirementsCards":[{"key":"BLUE","value":1}],"requirementsCardsLevel":2},{"type":"ProductionLeader","production":{"input":[0,0,1,0,0,0,0],"restoreinput":[0,0,1,0,0,0,0],"output":[0,0,0,0,1,0,1],"restoreoutput":[0,0,0,0,1,0,1]},"state":"INACTIVE","victoryPoints":4,"requirementsResources":[],"requirementsCards":[{"key":"YELLOW","value":1}],"requirementsCardsLevel":2},{"type":"MarketLeader","bonus":"GOLD","state":"INACTIVE","victoryPoints":5,"requirementsResources":[],"requirementsCards":[{"key":"PURPLE","value":2},{"key":"GREEN","value":1}],"requirementsCardsLevel":1},{"type":"MarketLeader","bonus":"STONE","state":"INACTIVE","victoryPoints":5,"requirementsResources":[],"requirementsCards":[{"key":"BLUE","value":2},{"key":"YELLOW","value":1}],"requirementsCardsLevel":1},{"type":"MarketLeader","bonus":"SHIELD","state":"INACTIVE","victoryPoints":5,"requirementsResources":[],"requirementsCards":[{"key":"GREEN","value":2},{"key":"PURPLE","value":1}],"requirementsCardsLevel":1},{"type":"MarketLeader","bonus":"SERVANT","state":"INACTIVE","victoryPoints":5,"requirementsResources":[],"requirementsCards":[{"key":"YELLOW","value":2},{"key":"BLUE","value":1}],"requirementsCardsLevel":1},{"type":"DepositLeader","leaderdepot":{"res_sel":[{"key":"EMPTY","value":false},{"key":"EMPTY","value":false}],"globalPositionOfFirstElement":0,"numberOfOccupiedSpots":0,"type":"GOLD"},"state":"INACTIVE","victoryPoints":3,"requirementsResources":[{"key":"SHIELD","value":5}],"requirementsCards":[],"requirementsCardsLevel":1},{"type":"DepositLeader","leaderdepot":{"res_sel":[{"key":"EMPTY","value":false},{"key":"EMPTY","value":false}],"globalPositionOfFirstElement":0,"numberOfOccupiedSpots":0,"type":"SHIELD"},"state":"INACTIVE","victoryPoints":3,"requirementsResources":[{"key":"SERVANT","value":5}],"requirementsCards":[],"requirementsCardsLevel":1},{"type":"DepositLeader","leaderdepot":{"res_sel":[{"key":"EMPTY","value":false},{"key":"EMPTY","value":false}],"globalPositionOfFirstElement":0,"numberOfOccupiedSpots":0,"type":"SERVANT"},"state":"INACTIVE","victoryPoints":3,"requirementsResources":[{"key":"STONE","value":5}],"requirementsCards":[],"requirementsCardsLevel":1},{"type":"DepositLeader","leaderdepot":{"res_sel":[{"key":"EMPTY","value":false},{"key":"EMPTY","value":false}],"globalPositionOfFirstElement":0,"numberOfOccupiedSpots":0,"type":"STONE"},"state":"INACTIVE","victoryPoints":3,"requirementsResources":[{"key":"GOLD","value":5}],"requirementsCards":[],"requirementsCardsLevel":1},{"type":"DevelopmentDiscountLeader","discount":{"key":"GOLD","value":1},"state":"INACTIVE","victoryPoints":2,"requirementsResources":[],"requirementsCards":[{"key":"YELLOW","value":1},{"key":"PURPLE","value":1}],"requirementsCardsLevel":1},{"type":"DevelopmentDiscountLeader","discount":{"key":"STONE","value":1},"state":"INACTIVE","victoryPoints":2,"requirementsResources":[],"requirementsCards":[{"key":"GREEN","value":1},{"key":"BLUE","value":1}],"requirementsCardsLevel":1},{"type":"DevelopmentDiscountLeader","discount":{"key":"SHIELD","value":1},"state":"INACTIVE","victoryPoints":2,"requirementsResources":[],"requirementsCards":[{"key":"PURPLE","value":1},{"key":"BLUE","value":1}],"requirementsCardsLevel":1},{"type":"DevelopmentDiscountLeader","discount":{"key":"SHIELD","value":1},"state":"INACTIVE","victoryPoints":2,"requirementsResources":[],"requirementsCards":[{"key":"PURPLE","value":1},{"key":"BLUE","value":1}],"requirementsCardsLevel":1}]